{"assets":{"B280C02F11574078376F57CA1018451D":{"type":"texture","index":15,"assetRequest":{"type":"slide","state":"incoming","slide":"35A0C73F-D6FE-4134-8ED5-14A343607819"},"url":{"web":"assets/B280C02F11574078376F57CA1018451D.svg"},"width":1920,"height":1080},"09C7CE9331CE2F4194262E7F6B4D0E6E":{"type":"texture","index":14,"assetRequest":{"type":"slide","state":"outgoing","slide":"B8B16762-ECA5-4479-9306-C441428A4B10"},"url":{"web":"assets/09C7CE9331CE2F4194262E7F6B4D0E6E.svg"},"width":1920,"height":1080}},"events":[{"effects":[{"beginTime":0,"baseLayer":{"animations":[],"initialState":{"affineTransform":[1,0,0,1,0,0],"masksToBounds":false,"rotation":0,"scale":1,"position":{"pointX":960,"pointY":540},"width":1920,"sublayerTransform":[1,0,0,0,0,1,0,0,0,0,1,0,0,0,0,1],"contentsRect":{"y":0,"x":0,"width":1,"height":1},"opacity":1,"edgeAntialiasingMask":251658240,"height":1080,"hidden":false,"anchorPoint":{"pointX":0.5,"pointY":0.5}},"objectID":"0","layers":[{"animations":[],"initialState":{"affineTransform":[1,0,0,1,0,0],"masksToBounds":false,"rotation":0,"scale":1,"position":{"pointX":960,"pointY":540},"width":1920,"sublayerTransform":[1,0,0,0,0,1,0,0,0,0,1,-0.0003500791246677598,0,0,0,1],"contentsRect":{"y":0,"x":0,"width":1,"height":1},"opacity":1,"edgeAntialiasingMask":251658240,"height":1080,"hidden":false,"anchorPoint":{"pointX":0.5,"pointY":0.5}},"layers":[{"animations":[],"layers":[],"initialState":{"affineTransform":[1,0,0,1,0,0],"masksToBounds":false,"rotation":0,"scale":1,"position":{"pointX":960,"pointY":540},"width":1920,"sublayerTransform":[1,0,0,0,0,1,0,0,0,0,1,0,0,0,0,1],"contentsRect":{"y":0,"x":0,"width":1,"height":1},"opacity":1,"edgeAntialiasingMask":0,"height":1080,"hidden":false,"anchorPoint":{"pointX":0.5,"pointY":0.5}},"texture":"B280C02F11574078376F57CA1018451D"},{"animations":[{"timeOffset":0,"from":{"scalar":false},"beginTime":0,"repeatCount":0,"fillMode":"both","property":"hidden","autoreverses":false,"duration":0.01,"to":{"scalar":true}}],"layers":[],"initialState":{"affineTransform":[1,0,0,1,0,0],"masksToBounds":false,"rotation":0,"scale":1,"position":{"pointX":960,"pointY":540},"width":1920,"sublayerTransform":[1,0,0,0,0,1,0,0,0,0,1,0,0,0,0,1],"contentsRect":{"y":0,"x":0,"width":1,"height":1},"opacity":1,"edgeAntialiasingMask":0,"height":1080,"hidden":false,"anchorPoint":{"pointX":0.5,"pointY":0.5}},"texture":"09C7CE9331CE2F4194262E7F6B4D0E6E"}]}]},"effects":[],"duration":0.01,"type":"transition","name":"none","objectID":"0"}],"automaticPlay":false,"hyperlinks":[{"url":"https://github.com/atom/electron/blob/99e2871be1efa3ac66dd67ca61866bf439aa00be/docs/faq/electron-faq.md#i-can-not-use-jqueryrequirejsmeteorangularjs-in-electron","targetRectangle":{"y":143.0632219314575,"x":1181.035083770752,"width":33.0615234375,"height":35}},{"url":"https://blog.outsider.ne.kr/1170","targetRectangle":{"y":143.0632219314575,"x":1227.470630645752,"width":33.0615234375,"height":35}},{"url":"https://github.com/atom/libchromiumcontent","targetRectangle":{"y":236.0632219314575,"x":1312.768480420113,"width":453.7841796875,"height":58}},{"url":"https://github.com/atom/electron/commit/4af219089066ca515a18aedfb5603bf9248e73cd","targetRectangle":{"y":585.0632219314575,"x":869.814380645752,"width":81.8115234375,"height":35}},{"url":"https://nodejs.org/en/docs/es6/","targetRectangle":{"y":620.0632219314575,"x":869.814380645752,"width":475.9130859375,"height":35}},{"url":"https://www.npmjs.com/","targetRectangle":{"y":690.0632219314575,"x":1324.047780275345,"width":524.267578125,"height":58}}],"accessibility":[{"text":"Any Web Frameworks and Libraries","targetRectangle":{"y":50.06322193145752,"x":834.8143788576126,"width":788.0859375,"height":58}},{"text":"React, AngularJS, Polymer, WinJS, jQuery, Bootstrap, Photonkit …","targetRectangle":{"y":108.0632219314575,"x":869.814380645752,"width":868.1689453125,"height":35}},{"text":"Node integration issue [1], [2]","targetRectangle":{"y":143.0632219314575,"x":869.814380645752,"width":390.7177734375,"height":35}},{"text":"Latest Chromium via libchromiumcontent","targetRectangle":{"y":236.0632219314575,"x":834.8143788576126,"width":931.73828125,"height":58}},{"text":"Chromium Content API, Webkit API(V8)","targetRectangle":{"y":294.0632219314575,"x":869.814380645752,"width":522.5537109375,"height":35}},{"text":"Bumped new stable Chrome version within one or two weeks after release","targetRectangle":{"y":329.0632219314575,"x":869.814380645752,"width":990.1025390625,"height":35}},{"text":"Chromium: v47.0.2526.110, V8: v4.7.80.27","targetRectangle":{"y":364.0632219314575,"x":869.814380645752,"width":568.2275390625,"height":35}},{"text":"Stable and Latest APIs on Node.js","targetRectangle":{"y":457.0632219314575,"x":834.8143818378448,"width":761.865234375,"height":58}},{"text":"Upgrading after a month to avoid bugs","targetRectangle":{"y":515.0632219314575,"x":869.814380645752,"width":517.6611328125,"height":35}},{"text":"Ready to latest features going with V8 upgrades","targetRectangle":{"y":550.0632219314575,"x":869.814380645752,"width":644.560546875,"height":35}},{"text":"v5.1.1 (Node.js stable v5.4.1)","targetRectangle":{"y":585.0632219314575,"x":869.814380645752,"width":391.0107421875,"height":35}},{"text":"ES2015 shipping features is default","targetRectangle":{"y":620.0632219314575,"x":869.814380645752,"width":475.9130859375,"height":35}},{"text":"Supporting from over 200,000 npm packages ","targetRectangle":{"y":690.0632219314575,"x":834.8143818378448,"width":1025.9521484375,"height":58}},{"text":"browser.png","targetRectangle":{"y":193.859375,"x":227.0260620117188,"width":271,"height":234}},{"text":"by Electron v0.36.4 -2016/01/16","targetRectangle":{"y":1046.504760146141,"x":1592.481936454773,"width":320.1171875,"height":25}},{"text":"Web Tech","targetRectangle":{"y":474.66668176651,"x":189.1080856323242,"width":346.8359375,"height":94}},{"text":"Use HTML, CSS, and JavaScript with Chromium and Node.js to build your app","targetRectangle":{"y":626.66668176651,"x":105.6290817260742,"width":526.220703125,"height":232}}],"baseLayer":{"animations":[],"initialState":{"affineTransform":[1,0,0,1,0,0],"masksToBounds":false,"rotation":0,"scale":1,"position":{"pointX":960,"pointY":540},"width":1920,"sublayerTransform":[1,0,0,0,0,1,0,0,0,0,1,0,0,0,0,1],"contentsRect":{"y":0,"x":0,"width":1,"height":1},"opacity":1,"edgeAntialiasingMask":251658240,"height":1080,"hidden":false,"anchorPoint":{"pointX":0.5,"pointY":0.5}},"objectID":"0","layers":[{"animations":[],"initialState":{"affineTransform":[1,0,0,1,0,0],"masksToBounds":false,"rotation":0,"scale":1,"position":{"pointX":960,"pointY":540},"width":1920,"sublayerTransform":[1,0,0,0,0,1,0,0,0,0,1,-0.0003500791246677598,0,0,0,1],"contentsRect":{"y":0,"x":0,"width":1,"height":1},"opacity":1,"edgeAntialiasingMask":251658240,"height":1080,"hidden":false,"anchorPoint":{"pointX":0.5,"pointY":0.5}},"layers":[{"animations":[],"layers":[],"initialState":{"affineTransform":[1,0,0,1,0,0],"masksToBounds":false,"rotation":0,"scale":1,"position":{"pointX":960,"pointY":540},"width":1920,"sublayerTransform":[1,0,0,0,0,1,0,0,0,0,1,0,0,0,0,1],"contentsRect":{"y":0,"x":0,"width":1,"height":1},"opacity":1,"edgeAntialiasingMask":0,"height":1080,"hidden":false,"anchorPoint":{"pointX":0.5,"pointY":0.5}},"texture":"09C7CE9331CE2F4194262E7F6B4D0E6E"}]}]}}]}